libdyson_rest/__init__.py
libdyson_rest/async_client.py
libdyson_rest/client.py
libdyson_rest/exceptions.py
libdyson_rest/types.py
libdyson_rest/validation.py
libdyson_rest/models/__init__.py
libdyson_rest/models/auth.py
libdyson_rest/models/device.py
libdyson_rest/models/iot.py
libdyson_rest/utils/__init__.py
libdyson_rest-0.11.2.dist-info/licenses/LICENSE
libdyson_rest-0.11.2.dist-info/METADATA
libdyson_rest-0.11.2.dist-info/WHEEL
libdyson_rest-0.11.2.dist-info/top_level.txt
libdyson_rest-0.11.2.dist-info/RECORD
