Metadata-Version: 2.4
Name: libdyson-rest
Version: 0.11.2
Summary: Python library for interacting with Dyson devices through their official REST API
Author-email: Christopher Gray <79777799+cmgrayb@users.noreply.github.com>
Maintainer-email: Christopher Gray <79777799+cmgrayb@users.noreply.github.com>
License-Expression: MIT
Project-URL: Homepage, https://github.com/cmgrayb/libdyson-rest
Project-URL: Repository, https://github.com/cmgrayb/libdyson-rest
Project-URL: Documentation, https://github.com/cmgrayb/libdyson-rest#readme
Project-URL: Issues, https://github.com/cmgrayb/libdyson-rest/issues
Project-URL: Changelog, https://github.com/cmgrayb/libdyson-rest/blob/main/CHANGELOG.md
Keywords: dyson,air-purifier,fan,iot,rest-api,mqtt,home-automation
Classifier: Development Status :: 4 - Beta
Classifier: Intended Audience :: Developers
Classifier: Programming Language :: Python :: 3
Classifier: Programming Language :: Python :: 3.10
Classifier: Programming Language :: Python :: 3.11
Classifier: Programming Language :: Python :: 3.12
Classifier: Programming Language :: Python :: 3.13
Classifier: Topic :: Home Automation
Classifier: Topic :: Internet :: WWW/HTTP :: Dynamic Content
Classifier: Topic :: Software Development :: Libraries :: Python Modules
Requires-Python: >=3.10
License-File: LICENSE
Requires-Dist: requests>=2.28.0
Requires-Dist: httpx>=0.24.0
Requires-Dist: cryptography>=3.4.0
Requires-Dist: typing_extensions>=4.0.0
Provides-Extra: dev
Requires-Dist: ruff==0.14.14; extra == "dev"
Requires-Dist: pytest==9.0.2; extra == "dev"
Requires-Dist: pytest-cov==7.0.0; extra == "dev"
Requires-Dist: pytest-asyncio==1.3.0; extra == "dev"
Requires-Dist: mypy==1.19.1; extra == "dev"
Requires-Dist: bandit[toml]==1.9.3; extra == "dev"
Requires-Dist: safety==4.0.4; extra == "dev"
Dynamic: license-file
